pyssertive/__init__.py
pyssertive/db.py
pyssertive/http/__init__.py
pyssertive/http/assertions.py
pyssertive/http/client.py
pyssertive/http/debug.py
pyssertive/http/django.py
pyssertive/http/request.py
pyssertive-0.2.3.dist-info/licenses/LICENSE
pyssertive-0.2.3.dist-info/METADATA
pyssertive-0.2.3.dist-info/WHEEL
pyssertive-0.2.3.dist-info/top_level.txt
pyssertive-0.2.3.dist-info/RECORD
