Metadata-Version: 2.4
Name: pyssertive
Version: 0.2.3
Summary: Fluent, chainable assertions for Django tests. Inspired by Laravel's elegant testing API.
Author-email: Unay Santisteban <usantisteban@othercode.io>
License: Apache-2.0
Project-URL: Homepage, https://github.com/othercodes/pyssertive
Project-URL: Repository, https://github.com/othercodes/pyssertive.git
Project-URL: Issues, https://github.com/othercodes/pyssertive/issues
Keywords: django,testing,assertions,fluent,pytest
Classifier: Development Status :: 4 - Beta
Classifier: Intended Audience :: Developers
Classifier: License :: OSI Approved :: Apache Software License
Classifier: Operating System :: OS Independent
Classifier: Programming Language :: Python :: 3
Classifier: Programming Language :: Python :: 3.11
Classifier: Programming Language :: Python :: 3.12
Classifier: Programming Language :: Python :: 3.13
Classifier: Framework :: Django
Classifier: Framework :: Django :: 4.2
Classifier: Framework :: Django :: 5.0
Classifier: Framework :: Django :: 5.1
Classifier: Framework :: Pytest
Classifier: Topic :: Software Development :: Testing
Classifier: Typing :: Typed
Requires-Python: >=3.11
License-File: LICENSE
Requires-Dist: Django>=4.2
Dynamic: license-file
